engpy/__init__.py
engpy/interface.py
engpy/path.py
engpy/AI/__init__.py
engpy/AI/engine.py
engpy/AI/helpers.py
engpy/AI/settings.py
engpy/arrays/__init__.py
engpy/arrays/matrix.py
engpy/arrays/vector.py
engpy/classes/__init__.py
engpy/classes/subclass.py
engpy/errors/__init__.py
engpy/errors/exceptions.py
engpy/errors/warnings.py
engpy/errors/wreck.py
engpy/fundamentals/__init__.py
engpy/fundamentals/primary.py
engpy/lib/__init__.py
engpy/lib/misc.py
engpy/lib/SS/__init__.py
engpy/lib/SS/progressions.py
engpy/lib/SS/series.py
engpy/lib/SS/ss.py
engpy/lib/transforms/__init__.py
engpy/lib/transforms/laplace.py
engpy/lib/transforms/various.py
engpy/lib/transforms/ztransform.py
engpy/misc/__init__.py
engpy/misc/abilities.py
engpy/misc/assist.py
engpy/misc/gen.py
engpy/misc/helpers.py
engpy/misc/imports.py
engpy/misc/internals.py
engpy/misc/miscs.py
engpy/misc/omissions.py
engpy/misc/pabilities.py
engpy/misc/strict.py
engpy/misc/tables.py
engpy/misc/utilities.py
engpy/misc/vars.py
engpy/misc/scan/__init__.py
engpy/misc/scan/scan_expr.py
engpy/oblects/KnowledgeBase.py
engpy/oblects/__init__.py
engpy/oblects/abc.py
engpy/oblects/assist.py
engpy/oblects/cls.py
engpy/oblects/states.py
engpy/repl/__init__.py
engpy/repl/compiles.py
engpy/tools/__init__.py
engpy/tools/_fractions.py
engpy/tools/exprs.py
engpy/tools/series.py
engpy/tools/math/__init__.py
engpy/tools/math/core.py
engpy/tools/math/misc.py
engpy/tools/math/trigs.py
engpy/visuals/__init__.py
engpy/visuals/graph.py
engpy-1.0.6.dist-info/License.txt
engpy-1.0.6.dist-info/METADATA
engpy-1.0.6.dist-info/WHEEL
engpy-1.0.6.dist-info/top_level.txt
engpy-1.0.6.dist-info/RECORD
