Metadata-Version: 2.1
Name: engpy
Version: 1.0.6
Summary: Python for Engineering
Home-page: https://github.com/miracle5284/engpy.git
Author: Miracle Adebunmi
Author-email: miraclem2014@gmail.com
License: MIT
Platform: UNKNOWN
Classifier: Programming Language :: Python :: 3
Classifier: License :: OSI Approved :: MIT License
Classifier: Operating System :: OS Independent
Requires-Python: >=3.5
Requires-Dist: matplotlib (>=3.1.0)
